CHANGES.rst
MANIFEST.in
README.rst
buildout.cfg
setup.py
docs/LICENSE.GPL
docs/LICENSE.txt
src/Products/__init__.py
src/Products.MeetingSeraing.egg-info/PKG-INFO
src/Products.MeetingSeraing.egg-info/SOURCES.txt
src/Products.MeetingSeraing.egg-info/dependency_links.txt
src/Products.MeetingSeraing.egg-info/namespace_packages.txt
src/Products.MeetingSeraing.egg-info/not-zip-safe
src/Products.MeetingSeraing.egg-info/requires.txt
src/Products.MeetingSeraing.egg-info/top_level.txt
src/Products/MeetingSeraing/README.txt
src/Products/MeetingSeraing/__init__.py
src/Products/MeetingSeraing/adapters.py
src/Products/MeetingSeraing/config.py
src/Products/MeetingSeraing/configure.zcml
src/Products/MeetingSeraing/ecolsanit.py
src/Products/MeetingSeraing/events.py
src/Products/MeetingSeraing/events.zcml
src/Products/MeetingSeraing/interfaces.py
src/Products/MeetingSeraing/overrides.zcml
src/Products/MeetingSeraing/profiles.zcml
src/Products/MeetingSeraing/refresh.txt
src/Products/MeetingSeraing/setuphandlers.py
src/Products/MeetingSeraing/testing.py
src/Products/MeetingSeraing/testing.zcml
src/Products/MeetingSeraing/version.txt
src/Products/MeetingSeraing/Extensions/__init__.py
src/Products/MeetingSeraing/browser/__init__.py
src/Products/MeetingSeraing/browser/configure.zcml
src/Products/MeetingSeraing/browser/meeting.py
src/Products/MeetingSeraing/browser/messages.pt
src/Products/MeetingSeraing/browser/overrides.py
src/Products/MeetingSeraing/browser/simple_meeting.pt
src/Products/MeetingSeraing/browser/viewlets.py
src/Products/MeetingSeraing/locales/PloneMeeting.pot
src/Products/MeetingSeraing/locales/datagridfield.pot
src/Products/MeetingSeraing/locales/imio.actionspanel.pot
src/Products/MeetingSeraing/locales/imio.history.pot
src/Products/MeetingSeraing/locales/plone.pot
src/Products/MeetingSeraing/locales/sync_pos.sh
src/Products/MeetingSeraing/locales/fr/LC_MESSAGES/PloneMeeting.po
src/Products/MeetingSeraing/locales/fr/LC_MESSAGES/datagridfield.po
src/Products/MeetingSeraing/locales/fr/LC_MESSAGES/imio.actionspanel.po
src/Products/MeetingSeraing/locales/fr/LC_MESSAGES/imio.history.po
src/Products/MeetingSeraing/locales/fr/LC_MESSAGES/plone.po
src/Products/MeetingSeraing/migrations/__init__.py
src/Products/MeetingSeraing/migrations/migrate_to_4200.py
src/Products/MeetingSeraing/migrations/migrate_to_4_1.py
