Metadata-Version: 2.1
Name: Products.MeetingSeraing
Version: 4.2.12
Summary: PloneMeeting profile for city of Seraing
Home-page: http://www.imio.be/produits/gestion-des-deliberations
Author: Andre Nuyens
Author-email: andre.nuyens@imio.be
License: GPL
Platform: UNKNOWN
Classifier: Environment :: Web Environment
Classifier: Framework :: Plone
Classifier: Framework :: Plone :: 4.3
Classifier: Programming Language :: Python
Classifier: Programming Language :: Python :: 2.7
Provides-Extra: templates
Provides-Extra: test
